softnanotools/__init__.py
softnanotools/_version.py
softnanotools/cli.py
softnanotools/generate/__init__.py
softnanotools/generate/_components.py
softnanotools/generate/_module.py
softnanotools/generate/_package.py
softnanotools/generate/_project.py
softnanotools/generate/_script.py
softnanotools/generate/_tests.py
softnanotools/generate/cli.py
softnanotools/generate/assets/.gitattributes.template
softnanotools/generate/assets/.gitignore.template
softnanotools/generate/assets/.pre-commit-config.yaml.template
softnanotools/generate/assets/MANIFEST.in.template
softnanotools/generate/assets/README.md.template
softnanotools/generate/assets/__init__.py.template
softnanotools/generate/assets/_version.py.template
softnanotools/generate/assets/coverage.yml.template
softnanotools/generate/assets/pyproject.toml.template
softnanotools/generate/assets/quick-build.yml.template
softnanotools/generate/assets/setup.cfg.template
softnanotools/generate/assets/setup.py.template
softnanotools/generate/assets/versioneer.py.template
softnanotools/generate/git/__init__.py
softnanotools/generate/git/_actions.py
softnanotools/js/__init__.py
softnanotools/js/cli.py
softnanotools/js/core.py
softnanotools/logger/__init__.py
softnanotools/logger/_logger.py
softnanotools/notebooks/__init__.py
softnanotools/notebooks/_core.py
softnanotools/notebooks/_utils.py
softnanotools/runner/__init__.py
softnanotools/runner/_runner.py
softnanotools/timer/__init__.py
softnanotools/timer/_timer.py
softnanotools-0.7.0.dist-info/LICENSE
softnanotools-0.7.0.dist-info/METADATA
softnanotools-0.7.0.dist-info/WHEEL
softnanotools-0.7.0.dist-info/entry_points.txt
softnanotools-0.7.0.dist-info/top_level.txt
softnanotools-0.7.0.dist-info/RECORD
