Metadata-Version: 2.1
Name: softnanotools
Version: 0.7.0
Summary: Tools for computing
Home-page: https://github.com/softnanolab/softnanotools
Author: Debesh Mandal
Classifier: Programming Language :: Python :: 3
Classifier: License :: OSI Approved :: MIT License
Classifier: Operating System :: OS Independent
Requires-Python: >=3.5
License-File: LICENSE
